fhirsnake/.gitignore
fhirsnake/__init__.py
fhirsnake/files.py
fhirsnake/main.py
fhirsnake-1.1.0.dist-info/METADATA
fhirsnake-1.1.0.dist-info/WHEEL
fhirsnake-1.1.0.dist-info/RECORD
