Metadata-Version: 2.1
Name: fhirsnake
Version: 1.1.0
Summary: A minimalistic FHIR server for resources as files
Home-page: https://github.com/beda-software/fhirsnake/
Author: Ilya Beda
Author-email: ilya@beda.software
Requires-Python: >=3.11,<4.0
Classifier: Programming Language :: Python :: 3
Classifier: Programming Language :: Python :: 3.11
Classifier: Programming Language :: Python :: 3.12
Requires-Dist: fastapi (>=0.112.1,<0.113.0)
Requires-Dist: pyyaml (>=6.0.2,<7.0.0)
Requires-Dist: uvicorn (>=0.30.6,<0.31.0)
